setup.py
uninstall_app/__init__.py
uninstall_app.egg-info/PKG-INFO
uninstall_app.egg-info/SOURCES.txt
uninstall_app.egg-info/dependency_links.txt
uninstall_app.egg-info/entry_points.txt
uninstall_app.egg-info/top_level.txt