Metadata-Version: 1.0
Name: uninstall-app
Version: 0.0.1
Summary: 自动化卸载app
Home-page: https://allenwu.itscoder.com
Author: allen
Author-email: 437806668@qq.com
License: UNKNOWN
Platform: UNKNOWN
